LICENSE
README.md
setup.py
DataGenerator/__init__.py
DataGenerator/Attribute/CaseAttribute.py
DataGenerator/Attribute/IsAdjectiveAttribute.py
DataGenerator/Attribute/IsAuxiliaryVerbAttribute.py
DataGenerator/Attribute/IsCapitalAttribute.py
DataGenerator/Attribute/IsDateAttribute.py
DataGenerator/Attribute/IsFractionAttribute.py
DataGenerator/Attribute/IsHonorificAttribute.py
DataGenerator/Attribute/IsLocationGazetteer.py
DataGenerator/Attribute/IsMoneyAttribute.py
DataGenerator/Attribute/IsNumberAttribute.py
DataGenerator/Attribute/IsOrganizationAttribute.py
DataGenerator/Attribute/IsOrganizationGazetteer.py
DataGenerator/Attribute/IsPersonGazetteer.py
DataGenerator/Attribute/IsProperNounAttribute.py
DataGenerator/Attribute/IsRealAttribute.py
DataGenerator/Attribute/IsTimeAttribute.py
DataGenerator/Attribute/LastIGContainsPossessiveAttribute.py
DataGenerator/Attribute/LastIGContainsTagAblativeAttribute.py
DataGenerator/Attribute/LastIGContainsTagAccusativeAttribute.py
DataGenerator/Attribute/LastIGContainsTagAttribute.py
DataGenerator/Attribute/LastIGContainsTagGenitiveAttribute.py
DataGenerator/Attribute/LastIGContainsTagInstrumentalAttribute.py
DataGenerator/Attribute/MainPosAttribute.py
DataGenerator/Attribute/Predicate.py
DataGenerator/Attribute/RootFormAttribute.py
DataGenerator/Attribute/RootPosAttribute.py
DataGenerator/Attribute/SurfaceFormAttribute.py
DataGenerator/Attribute/__init__.py
DataGenerator/CorpusGenerator/NERCorpusGenerator.py
DataGenerator/CorpusGenerator/SentenceDisambiguationCorpusGenerator.py
DataGenerator/CorpusGenerator/TreeDisambiguationCorpusGenerator.py
DataGenerator/CorpusGenerator/__init__.py
DataGenerator/DatasetGenerator/AnnotatedDatasetGenerator.py
DataGenerator/DatasetGenerator/DataSetGenerator.py
DataGenerator/DatasetGenerator/DisambiguationDataSetGenerator.py
DataGenerator/DatasetGenerator/NerDataSetGenerator.py
DataGenerator/DatasetGenerator/RootWordDataSetGenerator.py
DataGenerator/DatasetGenerator/SemanticDataSetGenerator.py
NlpToolkit_DataGenerator.egg-info/PKG-INFO
NlpToolkit_DataGenerator.egg-info/SOURCES.txt
NlpToolkit_DataGenerator.egg-info/dependency_links.txt
NlpToolkit_DataGenerator.egg-info/requires.txt
NlpToolkit_DataGenerator.egg-info/top_level.txt