Metadata-Version: 2.1
Name: NlpToolkit-DataGenerator
Version: 1.0.6
Summary: Classification dataset generator library for high level Nlp tasks
Home-page: https://github.com/StarlangSoftware/DataGenerator-Py
Author: olcaytaner
Author-email: olcay.yildiz@ozyegin.edu.tr
License: UNKNOWN
Platform: UNKNOWN
License-File: LICENSE
